{"https://dwolla.com":{"score":70,"numberResources":68,"numberStaticResources":29,"speedIndex":2668,"loadTime":3945,"renderTime":3027.5,"pageSize":513628,"numberJsResources":15,"jsResponseBytes":79949,"numberCssResources":3,"cssResponseBytes":76754,"numberImageResources":40,"imageResponseBytes":252679,"numberOtherResources":11,"otherResponseBytes":6266},"https://dwolla.com/login":{"score":79,"numberResources":58,"numberStaticResources":19,"speedIndex":1805,"loadTime":3248.5,"renderTime":2567,"pageSize":216725,"numberJsResources":16,"jsResponseBytes":92370,"numberCssResources":3,"cssResponseBytes":14283,"numberImageResources":16,"imageResponseBytes":9046,"numberOtherResources":10,"otherResponseBytes":6266},"https://dwolla.com/about":{"score":78,"numberResources":74,"numberStaticResources":25,"speedIndex":2191,"loadTime":5536,"renderTime":3799,"pageSize":621046,"numberJsResources":16,"jsResponseBytes":141594,"numberCssResources":4,"cssResponseBytes":130722,"numberImageResources":35,"imageResponseBytes":233992,"numberOtherResources":11,"otherResponseBytes":6266},"https://dwolla.com/register":{"score":74,"numberResources":65,"numberStaticResources":25,"speedIndex":1906,"loadTime":3349,"renderTime":2612,"pageSize":297896,"numberJsResources":22,"jsResponseBytes":169249,"numberCssResources":3,"cssResponseBytes":14346,"numberImageResources":16,"imageResponseBytes":9206,"numberOtherResources":10,"otherResponseBytes":6266}}