{"https://dwolla.com":{"score":74,"numberResources":71,"numberStaticResources":30,"speedIndex":2279,"loadTime":3673.5,"renderTime":2605,"pageSize":673426,"numberJsResources":13,"jsResponseBytes":155719,"numberCssResources":3,"cssResponseBytes":187091,"numberImageResources":35,"imageResponseBytes":231197,"numberOtherResources":13,"otherResponseBytes":7135},"https://dwolla.com/login":{"score":79,"numberResources":60,"numberStaticResources":20,"speedIndex":1607,"loadTime":3386.5,"renderTime":2425,"pageSize":218037,"numberJsResources":17,"jsResponseBytes":102024,"numberCssResources":3,"cssResponseBytes":13793,"numberImageResources":16,"imageResponseBytes":9039,"numberOtherResources":11,"otherResponseBytes":6744},"https://dwolla.com/about":{"score":69,"numberResources":76,"numberStaticResources":26,"speedIndex":2452,"loadTime":5070.5,"renderTime":3246.5,"pageSize":623336,"numberJsResources":17,"jsResponseBytes":150818,"numberCssResources":4,"cssResponseBytes":129934,"numberImageResources":38,"imageResponseBytes":233596,"numberOtherResources":12,"otherResponseBytes":6744},"https://dwolla.com/register":{"score":74,"numberResources":67,"numberStaticResources":26,"speedIndex":1810,"loadTime":3861.5,"renderTime":2792,"pageSize":299198,"numberJsResources":23,"jsResponseBytes":178775,"numberCssResources":3,"cssResponseBytes":13873,"numberImageResources":16,"imageResponseBytes":9165,"numberOtherResources":11,"otherResponseBytes":6744}}